{
  "icons": [
    {
      "src": "/giraffe/icon_512x512.ae025c6c47ee5b877857823ae993dc33.png",
      "sizes": "512x512",
      "type": "image/png"
    },
    {
      "src": "/giraffe/icon_192x192.46c1e3d90813454a521dcab70df0662d.png",
      "sizes": "192x192",
      "type": "image/png"
    },
    {
      "src": "/giraffe/icon_64x64.162eec184045c636cf4c5a9c1a5f1e8a.png",
      "sizes": "64x64",
      "type": "image/png"
    }
  ],
  "name": "Giraffe",
  "short_name": "Giraffe",
  "orientation": "portrait",
  "display": "standalone",
  "start_url": ".",
  "description": "Giraffe - Simple Imgur client",
  "background_color": "#ffffff",
  "theme_color": "#13809b"
}